qAuth/__init__.py
qAuth/ent/__init__.py
qAuth/ent/liBarnum.py
qAuth/examples/__init__.py
qAuth/examples/liBarnum/__init__.py
qAuth/examples/liBarnum/alice.py
qAuth/examples/liBarnum/bob.py
qAuth/examples/pingPong/__init__.py
qAuth/examples/pingPong/alice.py
qAuth/examples/pingPong/bob.py
qAuth/examples/zwdz/__init__.py
qAuth/examples/zwdz/alice.py
qAuth/examples/zwdz/bob.py
qAuth/nonEnt/__init__.py
qAuth/nonEnt/pingPong.py
qAuth/nonEnt/zwdz.py
qAuth_rasa97-0.0.1.dist-info/LICENSE
qAuth_rasa97-0.0.1.dist-info/METADATA
qAuth_rasa97-0.0.1.dist-info/WHEEL
qAuth_rasa97-0.0.1.dist-info/top_level.txt
qAuth_rasa97-0.0.1.dist-info/RECORD
