Metadata-Version: 2.1
Name: qAuth-rasa97
Version: 0.0.1
Summary: Quantum Authentication Protocols libraries
Home-page: UNKNOWN
Author: Ravisankar A V
Author-email: rasa97uchiha@gmail.com
License: UNKNOWN
Platform: UNKNOWN
Requires-Dist: simulaqron (==2.1.1)
Requires-Dist: cqc (==2.1.0)
